leveloccur/__init__.py
leveloccur-1.0.0.dist-info/licenses/LICENSE
leveloccur-1.0.0.dist-info/METADATA
leveloccur-1.0.0.dist-info/WHEEL
leveloccur-1.0.0.dist-info/top_level.txt
leveloccur-1.0.0.dist-info/RECORD
