Metadata-Version: 2.4
Name: leveloccur
Version: 1.0.0
Summary: Provides a class to specify a level of something
Author-email: Ngô Trần Quang Thiện <quangthienngotran@gmail.com>
License: GPLv3
Keywords: level
Requires-Python: >=3.7
License-File: LICENSE
Dynamic: license-file
